{
    "2023-06-17 14:49:25.840379": [
        {
            "使用者": "我相出去玩～～～"
        },
        {
            "IJ": "計畫出去玩了？太棒了！作為一個旅遊助理，我可以幫你安排行程、查詢天氣等。請問你有任何特定的地點或活動想要參加嗎？讓我來給你一些建議吧！😄"
        }
    ],
    "2023-06-17 14:49:41.189796": [
        {
            "使用者": "去中世紀"
        },
        {
            "IJ": "紀啊，聽起來超有趣的！可以告訴我你想要去哪個地方的中世紀呢？比如說是歐洲的城堡、古老的村莊，還是其他由中世紀風格建造而成的景點呢？讓我幫你安排一下充滿浪漫卻又彷彿時光倒流至中世紀的行程吧！🏰💫"
        }
    ],
    "2023-06-17 14:50:07.390188": [
        {
            "使用者": "歐洲好了"
        },
        {
            "IJ": "的中世紀城堡和古老村莊聽起來真是讓人心癢癢呢！歐洲有很多迷人的中世紀景點，我稍微為你做一個行程規劃吧！\n\n第一天：\n早上先去英格蘭的溫莎城堡，那裡有一座精美絕倫的中世紀要塞，也是英國女王伊麗莎白二世休息和舉辦宴會的地方。\n\n下午到法國泰阿爾地區，探索義大利那代表樹木森林延伸而成的加斯科涅小河流域遺址。在那能看到許多克试图三角突出森林小冈高四７古 chèdbode沴飛行之居民 green山连嬰们conium opes胥ori得burgs岳 est.\n\n晚上則前往捷克共和國布拉格，在哈勃洞窟裡品味正宗中世紀風味晚餐。\n ＊＊＊＊\n怎麼樣？這只是其中幾個例子而已，如果你有特別喜愛或期望走的國家或城市，再告訴給IJ吧！我可以幫你安排更符合你口味的旅程。🌍✈️"
        }
    ]
}